pytest_smtpd/__init__.py
pytest_smtpd-0.1.0.dist-info/METADATA
pytest_smtpd-0.1.0.dist-info/WHEEL
pytest_smtpd-0.1.0.dist-info/licenses/LICENSE
pytest_smtpd-0.1.0.dist-info/RECORD
