Metadata-Version: 2.1
Name: pytest-smtpd
Version: 0.1.0
Summary: An SMTP server for testing built on aiosmtpd
Project-URL: Documentation, https://github.com/bebleo/pytest-smtpd#readme
Project-URL: Issues, https://github.com/bebleo/pytest-smtpd/issues
Project-URL: Source, https://github.com/bebleo/pytest-smtpd
Author-email: James Warne <bebleo@yahoo.com>
License-Expression: MIT
License-File: LICENSE
Keywords: email,pytest,smtp,testing
Classifier: Framework :: Pytest
Classifier: License :: OSI Approved :: MIT License
Classifier: Operating System :: OS Independent
Classifier: Programming Language :: Python :: 3
Classifier: Programming Language :: Python :: 3 :: Only
Classifier: Programming Language :: Python :: 3.7
Classifier: Programming Language :: Python :: 3.8
Classifier: Programming Language :: Python :: 3.9
Classifier: Programming Language :: Python :: 3.10
Classifier: Programming Language :: Python :: 3.11
Classifier: Programming Language :: Python :: Implementation :: CPython
Classifier: Programming Language :: Python :: Implementation :: PyPy
Requires-Python: <4,>=3.7
Requires-Dist: pytest
Requires-Dist: smtpdfix
Provides-Extra: dev
Requires-Dist: flake8; extra == 'dev'
Requires-Dist: isort; extra == 'dev'
Requires-Dist: mypy; extra == 'dev'
Requires-Dist: tox; extra == 'dev'
